{
    "questions": [
        {
            "question": "<span class=\"highlighted\">$ \\frac{d}{dx}\\int_{0}^{x}(x - t)^3 u(t)dt = ? $</span>",
            "variants": [{
                "title": "$ \\int_{0}^{x}3(x + t)^2u(t)dt $ "
            }, {
                "title": "$ \\int_{0}^{x}(x + t)^4u(t)dt $ "
            }, {
                "title": "$ \\int_{0}^{x}(x - t)^2u(t)dt $ "
            }, {
                "title": "$ \\int_{0}^{x}3(x - t)u(t)dt $ "
            }, {
                "title": "$ \\int_{0}^{x}3(x - t)^2u(t)dt $ "
            }],
            "answer": 4
        }, {
            "question": "<span class=\"highlighted\">Which </span>is the equivalent <span class=\"highlighted\">IVP </span>to the <span class=\"highlighted\">Integral equation</span><br><span class=\"highlighted\">$ u(x) = 2 + 3x + 5x^2 + \\int_{0}^{x}[ 1 + 2 (x - t)] u(t) dt \\ ? $</span>",
            "variants": [{
                "title": "$ u''(x) - 3u'(x) - u(x) = 10, u(0) = 0, \\ u′(0) = 0 $ "
            }, {
                "title": "$ u''(x) + u'(x) + 2u(x) = 10, u(0) = 2, \\ u′(0) = 5 $ "
            }, {
                "title": "$ u''(x) - u'(x) - 2u(x) = 1, u(0) = 5, \\ u′(0) = 2$ "
            }, {
                "title": "$ u''(x) - u'(x) - 2u(x) = 10, u(0) = 2, \\ u′(0) = 5 $ "
            }, {
                "title": "$ u''(x) - u'(x) - 2u(x) = 0, u(0) = 2, \\ u′(0) = 5 $ "
            }],
            "answer": 3
        }, {
            "question": "<span class=\"highlighted\">$ F(x) = \\int_{0}^{x} xt u(t) dt \\Rightarrow F''(x) = ?  $</span>",
            "variants": [{
                "title": "$ xu'(x) + 3x^2 u(x) $ "
            }, {
                "title": "$   xu'(x) + x^3 u(x) $ "
            }, {
                "title": "$ x^2u'(x) + 3x u(x) $ "
            }, {
                "title": "$   x^2u''(x) + x u'(x) $ "
            }, {
                "title": "$   x^2u''(x) + 3x u'(x) $ "
            }],
            "answer": 2
        }, {
            "question": "<span class=\"highlighted\">Which </span>is the equivalent <span class=\"highlighted\">IVP </span>to the <span class=\"highlighted\">Integral equation</span><br><span class=\"highlighted\">$ u(x) = 1 + x +  \\int_{0}^{x} (x - t)^2 u(t) dt \\ ? $</span>",
            "variants": [{
                "title": "$ u''(x) - u'(x) = 0; \\ u(0) =1,u'(0) = 1 $ "
            }, {
                "title": "$ u'''(x) = 2u'(x) + u(x), u(0) = u′(0) = 1, u''(0) =0 $ "
            }, {
                "title": "$ u''(x) = 2u(x), u(0) = u′(0) = 1, u''(0) =0 $ "
            }, {
                "title": "$ u'''(x) = 2u(x), u(0) = u′(0) = 1, u''(0) =0 $ "
            }, {
                "title": "$ u'''(x) =0, u(0) = u′(0) = 1, u''(0) =0 $ "
            }],
            "answer": 3
        },
        {
            "question": "<span class=\"highlighted\">$ \\frac{d}{dx}\\int_{0}^{x}(x - t)^3 u(t)dt = ? $</span>",
            "variants": [{
                "title": "$ \\int_{0}^{x}3(x + t)^2u(t)dt $ "
            }, {
                "title": "$ \\int_{0}^{x}(x + t)^4u(t)dt $ "
            }, {
                "title": "$ \\int_{0}^{x}(x - t)^2u(t)dt $ "
            }, {
                "title": "$ \\int_{0}^{x}3(x - t)u(t)dt $ "
            }, {
                "title": "$ \\int_{0}^{x}3(x - t)^2u(t)dt $ "
            }],
            "answer": 4
        }, {
            "question": "<span class=\"highlighted\">Which </span>is the equivalent <span class=\"highlighted\">IVP </span>to the <span class=\"highlighted\">Integral equation</span><br><span class=\"highlighted\">$ u(x) = 2 + 3x + 5x^2 + \\int_{0}^{x}[ 1 + 2 (x - t)] u(t) dt \\ ? $</span>",
            "variants": [{
                "title": "$ u''(x) - 3u'(x) - u(x) = 10, u(0) = 0, \\ u′(0) = 0 $ "
            }, {
                "title": "$ u''(x) + u'(x) + 2u(x) = 10, u(0) = 2, \\ u′(0) = 5 $ "
            }, {
                "title": "$ u''(x) - u'(x) - 2u(x) = 1, u(0) = 5, \\ u′(0) = 2$ "
            }, {
                "title": "$ u''(x) - u'(x) - 2u(x) = 10, u(0) = 2, \\ u′(0) = 5 $ "
            }, {
                "title": "$ u''(x) - u'(x) - 2u(x) = 0, u(0) = 2, \\ u′(0) = 5 $ "
            }],
            "answer": 3
        }, {
            "question": "<span class=\"highlighted\">$ F(x) = \\int_{0}^{x} xt u(t) dt \\Rightarrow F''(x) = ?  $</span>",
            "variants": [{
                "title": "$ xu'(x) + 3x^2 u(x) $ "
            }, {
                "title": "$   xu'(x) + x^3 u(x) $ "
            }, {
                "title": "$ x^2u'(x) + 3x u(x) $ "
            }, {
                "title": "$   x^2u''(x) + x u'(x) $ "
            }, {
                "title": "$   x^2u''(x) + 3x u'(x) $ "
            }],
            "answer": 2
        }, {
            "question": "<span class=\"highlighted\">Which </span>is the equivalent <span class=\"highlighted\">IVP </span>to the <span class=\"highlighted\">Integral equation</span><br><span class=\"highlighted\">$ u(x) = 1 + x +  \\int_{0}^{x} (x - t)^2 u(t) dt \\ ? $</span>",
            "variants": [{
                "title": "$ u''(x) - u'(x) = 0; \\ u(0) =1,u'(0) = 1 $ "
            }, {
                "title": "$ u'''(x) = 2u'(x) + u(x), u(0) = u′(0) = 1, u''(0) =0 $ "
            }, {
                "title": "$ u''(x) = 2u(x), u(0) = u′(0) = 1, u''(0) =0 $ "
            }, {
                "title": "$ u'''(x) = 2u(x), u(0) = u′(0) = 1, u''(0) =0 $ "
            }, {
                "title": "$ u'''(x) =0, u(0) = u′(0) = 1, u''(0) =0 $ "
            }],
            "answer": 3
        },
        {
            "question": "<span class=\"highlighted\">Which </span>is the equivalent <span class=\"highlighted\">IVP </span>to the <span class=\"highlighted\">Integral equation</span><br><span class=\"highlighted\">$ u(x) = x - \\cos x + \\int_{0}^{x} (x - t) u(t) dt \\ ? $</span>",
            "variants": [{
                "title": "$ u''(x) - u'(x) = 0; \\ u(0) =1,u'(0) = 1 $ "
            }, {
                "title": "$ u''(x) - u(x) = \\sin x, u(0) = - 1, \\ u′(0) = 1 $ "
            }, {
                "title": "$ u''(x) + u(x) = \\cos x, u(0) = - 1, \\ u′(0) = 1 $ "
            }, {
                "title": "$ u''(x) - u(x) = \\cos x, u(0) = - 1, \\ u′(0) = 1 $ "
            }, {
                "title": "$ u''(x) - u'(x) = \\cos x, u(0) = 0, \\ u′(0) = 0 $ "
            }],
            "answer": 3
        }, {
            "question": "<span class=\"highlighted\">Which </span>is the equivalent <span class=\"highlighted\">IVP </span>to the <span class=\"highlighted\">Integral equation</span><br><span class=\"highlighted\">$ u(x) = x^2 + \\frac{1}{6}\\int_{0}^{x} (x - t)^3 u(t) dt \\ ? $</span>",
            "variants": [{
                "title": "$ u''(x) - u(x) = \\cos x, u(0) = 0,\\ u′(0) = 0 $ "
            }, {
                "title": "$ u'''(x) = 2u'(x) + u(x), u(0) = u′(0) = 1, u''(0) =0 $ "
            }, {
                "title": "u(4)(x)−4u(x)=0,u(0)=u′(0)=u‴(0)=2,  u″(0)=0$ u^{(4)}(x) - 4u(x) = 0, u(0) = u′(0) = u'''(0) = 2,\\ u''(0) = 0 $ "
            }, {
                "title": "$ u^{(4)}(x) + u(x) = 1, u(0) = u′(0) = u'''(0) = 0,\\ u''(0) = 2 $ "
            }, {
                "title": "$ u^{(4)}(x) - u(x) = 0, u(0) = u′(0) = u'''(0) = 0,\\ u''(0) = 2  $ "
            }],
            "answer": 4
        }, {
            "question": "<span class=\"highlighted\">$ \\frac{d}{dx}\\int_{x}^{4x} \\sin (x + t) u(t)dt = ? $</span>",
            "variants": [{
                "title": "$ \\sin 5x - \\sin x + \\int_{x}^{4x}\\sin (x + t) u(t)dt $ "
            }, {
                "title": "$ 4\\sin 5x + \\sin 2x - \\int_{x}^{4x}\\cos (x + t) u(t)dt $ "
            }, {
                "title": "$ 4\\cos 5x - \\cos 2x + \\int_{x}^{4x}\\cos (x + t) u(t)dt $ "
            }, {
                "title": "$ 4\\sin 5x - \\sin 2x + \\int_{x}^{4x}\\cos (x + t) u(t)dt $ "
            }, {
                "title": "$ \\int_{0}^{x}(x + t)^4u(t)dt $ "
            }],
            "answer": 3
        }, {
            "question": "<span class=\"highlighted\">$ F(x) = \\int_{0}^{x} e^{-x^2t^2} dt \\Rightarrow F'(x) = ? $</span>",
            "variants": [{
                "title": "$ e^{x^4} + \\int_{0}^{x} 2xe^{-x^2t^2}dt $ "
            }, {
                "title": "$ e^{-x^4} - \\int_{0}^{x} 2xe^{-x^2t^2}dt $ "
            }, {
                "title": "$ e^{-x^4} - \\int_{1}^{x} 2xe^{-x^2t^2}dt $ "
            }, {
                "title": "$ e^{x^2} - \\int_{0}^{x} xe^{x^2t^2}dt $ "
            }, {
                "title": "$ e^x + \\int_{0}^{x} x^2e^{-x^2t^2}dt $ "
            }],
            "answer": 1
        },
        {
            "question": "<span class=\"highlighted\">$ \\frac{d}{dx}(1 + xe^x ) = \\frac{d}{dx}( \\int_{0}^{x} e^{ x - t} u(t) dt) $</span>",
            "variants": [{
                "title": "$ (1 + x)e^x = u(x) + \\int_{0}^{x} e^{x-t} u(t) dt $ "
            }, {
                "title": "$ (1 + x)e^x = u(x) + \\int_{0}^{x} e^{x+t} u(t) dt $ "
            }, {
                "title": "$ e^x = u(x) - \\int_{0}^{x} e^{x-t} u(t) dt $ "
            }, {
                "title": "$   xe^x = 3u(x) + \\int_{0}^{x} e^{x+ t} u(t) dt $ "
            }, {
                "title": "$ (1 - x)e^x = u(x) - \\int_{0}^{x} e^{x-t} u(t) dt $ "
            }],
            "answer": 0
        }, {
            "question": "<span class=\"highlighted\">$ F(x) = \\int_{0}^{x} (x - t)^3 u(t) dt \\Rightarrow F^{(iv)}(x) = ? $</span>",
            "variants": [{
                "title": "$ \\int_{0}^{x}3(x - t)^2 u(t) dt $ "
            }, {
                "title": "$ u(x) $ "
            }, {
                "title": "$ 6 u(x) $ "
            }, {
                "title": "$ \\int_{0}^{x}6(x - t) u(t) dt $ "
            }, {
                "title": "$ \\int_{0}^{x}6 u(t) dt $ "
            }],
            "answer": 2
        }, {
            "question": "<span class=\"highlighted\">Which </span>is the equivalent <span class=\"highlighted\">IVP </span>to the <span class=\"highlighted\">Integral equation</span><br><span class=\"highlighted\">$ u(x) = -5 + 6x + \\int_{0}^{x}( 5 - 6x + 6t) u(t) dt \\ ? $</span>",
            "variants": [{
                "title": "$ u''(x) − 2u′(x) + 3u(x) = 0, u(0) = −3, u' (0) = −1 $ "
            }, {
                "title": "$ u''(x) + 5u′(x) - 6u(x) = 0, u(0) = −5, u' (0) = −19 $ "
            }, {
                "title": "$ u''(x) − 5u′(x) + 6u(x) = 0, u(0) = −5, u' (0) = −19 $ "
            }, {
                "title": "u″(x)−5u′(x)+6u(x)=0,u(0)=0,u′(0)=−9$ u''(x) − 5u′(x) + 6u(x) = 0, u(0) = 0, u' (0) = −9 $ "
            }, {
                "title": "$ u'''(x) − 5u′'(x) + 6u'(x) = 0, u(0) = −5, u' (0) = −19 $ "
            }],
            "answer": 2
        }, {
            "question": "<span class=\"highlighted\">Which </span>is the equivalent <span class=\"highlighted\">IVP </span>to the <span class=\"highlighted\">Integral equation</span><br><span class=\"highlighted\">$ u(x) = x^3 + \\int_{0}^{x}(x - t)^2 u(t) dt \\ ? $</span>",
            "variants": [{
                "title": "$ u'''(x) - 2u(x) = 6; \\ u(0) = u'(0) = u''(0) = 0 $ "
            }, {
                "title": "$ u'''(x) + 2u(x) = 6; \\ u(0) = u'(0) = u''(0) = 0 $ "
            }, {
                "title": "$ u'''(x) - 2u(x) = 0; \\ u(0) = u'(0) = u''(0) = 0 $ "
            }, {
                "title": "$ u''(x) - u'(x) = 0; \\ u(0) =1,u'(0) = 1 $ "
            }, {
                "title": "$ u'(x) - u(x) = 0; \\ u(0) = 0 $ "
            }],
            "answer": 0
        },
        {
            "question": "<span class=\"highlighted\">$ \\frac{d}{dx}(x^3 + \\frac{1}{6} x^6) = \\frac{d}{dx}( \\int_{0}^{x} (4 + x - t) u(t) dt) $</span>",
            "variants": [{
                "title": "$ 3x + x^2 = 4u'(x) + \\int_{0}^{x} u(t) dt) $ "
            }, {
                "title": "$ 3x^2 + x^5 = 4u(x) + \\int_{0}^{x} u(t) dt) $ "
            }, {
                "title": "$ x^2 + x^6 = u(x) + \\int_{0}^{x} u(t) dt) $ "
            }, {
                "title": "$ 3x^2 + x^5 = u(x) + \\int_{0}^{x} 2u(t) dt) $ "
            }, {
                "title": "$ 3x^2 - x^5 = 4u(x) - \\int_{0}^{x} u(t) dt) $ "
            }],
            "answer": 1
        }, {
            "question": "<span class=\"highlighted\">Which </span>is the equivalent <span class=\"highlighted\">IVP </span>to the <span class=\"highlighted\">Integral equation</span><br><span class=\"highlighted\">$ u(x) = x^4  + x^2 + 2\\int_{0}^{x} (x - t)^2 u(t) dt \\ ? $</span>",
            "variants": [{
                "title": "$ u'''(x) - 4u(x) = 2x, u(0) = u′(0) = 0, \\ u''(0) = 2 $ "
            }, {
                "title": "$ u'''(x) = 2u'(x) + u(x), u(0) = u′(0) = 1, u''(0) =0 $ "
            }, {
                "title": "$ u'''(x) + u(x) = 4x, u(0) = u′(0) = 1, \\ u''(0) = 2 $ "
            }, {
                "title": "$ u'''(x) - 4u(x) = 24x, u(0) = u′(0) = 0, \\ u''(0) = 2 $ "
            }, {
                "title": "$ u''(x) - u(x) = \\cos x, u(0) = 0,\\ u′(0) = 0 $ "
            }],
            "answer": 3
        }, {
            "question": "<span class=\"highlighted\">Which </span>is the equivalent <span class=\"highlighted\">IVP </span>to the <span class=\"highlighted\">Integral equation</span><br><span class=\"highlighted\">$ u(x) = e^x - \\int_{0}^{x} (x - t) u(t) dt \\ ? $</span>",
            "variants": [{
                "title": "$ u''(x) = 2u(x), u(0) = u′(0) = 1, u''(0) =0 $ "
            }, {
                "title": "$ u''(x) - u'(x) = 0; \\ u(0) =1,u'(0) = 1 $ "
            }, {
                "title": "$ u'''(x) = 2u'(x) + u(x), u(0) = u′(0) = 1, u''(0) =0 $ "
            }, {
                "title": "$ u'''(x) =0, u(0) = u′(0) = 1, u''(0) =0 $ "
            }, {
                "title": "$ u''(x) + u(x) = e^x, u(0) = u′(0) = 1 $ "
            }],
            "answer": 4
        }, {
            "question": "<span class=\"highlighted\">$ F(x) = \\int_{0}^{x} (x - t)^4 u(t) dt \\Rightarrow F'(x) = ? $</span>",
            "variants": [{
                "title": "$ \\int_{0}^{x} 3(x - t)^2 u(t) dt $ "
            }, {
                "title": "$ \\int_{0}^{x} 2(x - t) u(t) dt $ "
            }, {
                "title": "$ u(x) dt $ "
            }, {
                "title": "$ \\int_{0}^{x} u(t) dt $ "
            }, {
                "title": "$ \\int_{0}^{x} 4(x - t)^3 u(t) dt $ "
            }],
            "answer": 4
        },
        {
            "question": "<span class=\"highlighted\">$ F(x)=\\int_{0}^{x}(10x-6t)u(t)dt \\Rightarrow F'''(x)=?  $</span>",
            "variants": [{
                "title": "144xu'(x)+312u(x) "
            }, {
                "title": "16xu''(x)+724xu'(x)+612u(x) "
            }, {
                "title": "16x^2u''(x)+144xu'(x) "
            }, {
                "title": "16x^2u''(x)+144xu'(x)+312u(x) "
            }, {
                "title": "256x^2u''(x)+444u'(x)+312u(x) "
            }],
            "answer": 3
        },
        {
            "question": "<span class=\"highlighted\">Which </span>is the <span class=\"highlighted\">solution</span> of the  <br><span class=\"highlighted\">N</span><span class=\"highlighted\">onlinear  </span><span class=\"highlighted\">Volterra integral equation</span>  <br>of 1.kind<br><span class=\"highlighted\">$ \\frac{1}{2} \\sin x - \\frac{1}{2}x \\cos x = \\int_{0}^{x} \\sin (x - t) \\sin u(t) dt ? $</span>",
            "variants": [{
                "title": "$ u(x) = \\cos x $ "
            }, {
                "title": "$ u(x) = x^2 $ "
            }, {
                "title": "$ u(x) = x  $ "
            }, {
                "title": "$ u(x) = x^2 + x $ "
            }, {
                "title": "$ u(x) = \\sin x $ "
            }],
            "answer": 2
        }, {
            "question": "<span class=\"highlighted\">Which </span>is the <span class=\"highlighted\">solution</span> of the  <br><span class=\"highlighted\">N</span><span class=\"highlighted\">onlinear  </span><span class=\"highlighted\">Volterra integral equation</span>  <br>of 1.kind<br><span class=\"highlighted\">$ \\frac{1}{36}e^{6x} - \\frac{1}{6}x - \\frac{1}{36} = \\int_{0}^{x} (x - t) e^{2u(t)} dt ? $</span>",
            "variants": [{
                "title": "$ u(x) = -1 + 2x $ "
            }, {
                "title": "$ u(x) = 3x $ "
            }, {
                "title": "$ u(x) = 2x $ "
            }, {
                "title": "$ u(x) = 1 - x $ "
            }, {
                "title": "$ u(x) = 1 + x^2 $ "
            }],
            "answer": 1
        },
        {
            "question": "Which is the  <span class=\"highlighted\">solution </span>of the <span class=\"highlighted\">equation</span>  <br><span class=\"highlighted\">$ u(x) = 1 + x^2 + \\cos x − x − \\frac{1}{3}x^3 − sin x + \\int_0^x u(t)dt $</span><br><span class=\"highlighted\">(<b>Hint:</b>use Modified Decomposition Method)</span>",
            "variants": [{
                "title": "$ u(x) = 1 + x^2 + \\cos x $ "
            }, {
                "title": "$ u(x) = 1 + x^2 + \\sin x $ "
            }, {
                "title": "$ u(x) = 1 - x^2 - \\cos x $ "
            }, {
                "title": "$ u(x) = 1 - x^2 - \\sin x $ "
            }, {
                "title": "$ u(x) = 1 + x^2 + x^3 $ "
            }],
            "answer": 0
        }, {
            "question": "<span class=\"highlighted\">Which </span>is the <span class=\"highlighted\">converted </span>form of the  <br>Volterra Integral Equation of 1.kind<br><span class=\"highlighted\">$ e^x - \\cos x = \\int_0^x e^{x - t} u(t) dt $</span><br>  to the 2.kind ?",
            "variants": [{
                "title": "$ u(x) = e^x + \\sin x + \\int_0^x e^{x + t}u(t) dt $ "
            }, {
                "title": "$ u(x) = e^x + \\int_0^x e^{x - t}u(t) dt $ "
            }, {
                "title": "$ u(x) = \\sin x - \\int_0^x e^{x - t}u(t) dt $ "
            }, {
                "title": "$ u(x) = e^x + \\sin x - \\int_0^x e^{x - t}u(t) dt $ "
            }],
            "answer": 3
        }, {
            "question": "<span class=\"highlighted\">Which </span>is the solution of the equation<br><span class=\"highlighted\">$ u(x) =   2x + \\sec^2 x −  \\int_{-\\pi/4}^{\\pi/4} x u(t)dt $</span><br><b>(Hint: using The Successive Approximations Method )</b>",
            "variants": [{
                "title": "$ u(x) = \\sin x $ "
            }, {
                "title": "$ u(x) = 2\\sin x $ "
            }, {
                "title": "$ u(x) = 4e^x $ "
            }, {
                "title": "$ u(x) = \\cos x $ "
            }, {
                "title": "$ u(x) = \\sec^2 x $ "
            }],
            "answer": 4
        }, {
            "question": "<span class=\"highlighted\">Which </span>is the solution of the equation<br><span class=\"highlighted\">$ x = \\int_0^x (x − t + 1) u(t)dt \\ ? $</span><br>(Hint: using Laplace Transformation method)",
            "variants": [{
                "title": "$ u(x) = e^{2x} $ "
            }, {
                "title": "$ u(x) = x - \\sinh x $ "
            }, {
                "title": "$ u(x) = \\sinh x $ "
            }, {
                "title": "$ u(x) = e^{-x} $ "
            }],
            "answer": 3
        }, {
            "question": "Which is the  <span class=\"highlighted\">solution </span>of the <span class=\"highlighted\">equation</span>  <br><span class=\"highlighted\">$ u(x) = x - \\frac{2}{3}x^3 - 2 \\int_0^x u(t) dt \\ ? $</span><br><span class=\"highlighted\">(<b>Hint:</b>use Adomian Decomposition Method)</span>",
            "variants": [{
                "title": "$ u(x) = x - x^2 $ "
            }, {
                "title": "$ u(x) = 3x - 2x^2 $ "
            }, {
                "title": "$ u(x) = 1 + x^2 $ "
            }, {
                "title": "$ u(x) = x + x^2 $ "
            }, {
                "title": "$ u(x) = 4 - x $ "
            }],
            "answer": 0
        }, {
            "question": "Which is an <span class=\"highlighted\">eigenfunction </span>of the equation<br><span class=\"highlighted\">$ u(x) = \\lambda \\int_{0}^{\\pi} \\sin^2 x \\ u(t)dt \\   ? $</span>",
            "variants": [{
                "title": "$ u(x) = -\\frac{2}{\\pi}\\alpha \\sin^2 x $ "
            }, {
                "title": "$ u(x) = \\pi\\alpha \\sin^2 x $ "
            }, {
                "title": "$ u(x) = \\frac{2}{\\pi}\\alpha \\sin x $ "
            }, {
                "title": "$ u(x) = \\frac{2}{\\pi}\\alpha \\sin^2 x $ "
            }, {
                "title": "$ u(x) = \\frac{2}{\\pi}\\alpha \\cos^2 x $ "
            }],
            "answer": 3
        }, {
            "question": "Which is the  <span class=\"highlighted\">solution </span>of the <span class=\"highlighted\">equation</span>  <br><span class=\"highlighted\">$ u(x) = 1 - x - \\int_0^x (x - t) u(t)dt $</span><br><span class=\"highlighted\">(<b>Hint:</b>using The Successive Approximations Method)</span>",
            "variants": [{
                "title": "$ u(x) = \\cos x - \\sin x $ "
            }, {
                "title": "$ u(x) = \\cos x + \\sin x $ "
            }, {
                "title": "$ u(x) = \\cosh x $   "
            }, {
                "title": "$ u(x) =   e^x $ "
            }, {
                "title": "$ u(x) = \\cos x $   "
            }],
            "answer": 0
        }, {
            "question": "Which is the  <span class=\"highlighted\">solution </span>of the <span class=\"highlighted\">equation</span>  <br><span class=\"highlighted\">$ u(x) = \\frac{1}{2!}x^2 - \\int_0^x (x - t)u(t)dt $</span><br><span class=\"highlighted\">(<b>Hint:</b>using The Successive Substitution Method)</span>",
            "variants": [{
                "title": "$ u(x) = \\sin x $ "
            }, {
                "title": "$ u(x) = x + \\sin x $ "
            }, {
                "title": "$ u(x) = 2x - \\sin x $ "
            }, {
                "title": "$ u(x) = -1 + \\cos x $ "
            }, {
                "title": "$ u(x) = x - \\cos x $ "
            }],
            "answer": 3
        }, {
            "question": "Which is the  <span class=\"highlighted\">solution </span>of the <span class=\"highlighted\">equation</span>  <br><span class=\"highlighted\">$ u(x) = 1 - \\frac{1}{2}x^2 +\\frac{1}{6} \\int_0^x (x - t)^3 u(t)dt $</span><br><span class=\"highlighted\">(<b>Hint:</b>using The Laplace Transform Method )</span>",
            "variants": [{
                "title": "$ u(x) = \\cosh x $ "
            }, {
                "title": "$ u(x) = \\sinh x $ "
            }, {
                "title": "$ u(x) = \\sin x $   "
            }, {
                "title": "$ u(x) =   e^x $     "
            }, {
                "title": "$ u(x) = \\cos x $ "
            }],
            "answer": 4
        }, {
            "question": "<span class=\"highlighted\">Which </span>is the solution of the equation<br><span class=\"highlighted\">$ u(x) = sinx+ \\frac{1}{2} \\int_{0}^{\\pi/2} cosx\\ u(t)dt $</span><br><b>(Hint: using The Successive Substitution Method )</b>",
            "variants": [{
                "title": "$ $ u(x) = 2sinx + 3cosx $ $ "
            }, {
                "title": "$ u(x) = sinx + cosx $ "
            }, {
                "title": "$ $ u(x) = sin2x + cos2x $ $ "
            }, {
                "title": "$ u(x) = sinx - cosx $ "
            }, {
                "title": "$ $ u(x) = sinx $ "
            }],
            "answer": 1
        },
        {
            "question": "<span class=\"highlighted\">Which </span>is the equivalent <span class=\"highlighted\">IVP </span>to the <span class=\"highlighted\">Integral equation</span><br><span class=\"highlighted\">$ u(x) = x^4 + x^2 + 2\\int_{0}^{x}(x - t)^2 u(t) dt \\ ? $</span>",
            "variants": [{
                "title": "$ u''(x) + 4u(x) = 2x,u(0) = 0, u′(0) = 2 $ "
            }, {
                "title": "$ u'''(x) − 4u(x) = 24x,u(0) = 0, u′(0) = 0,u′'(0) = 2 $ "
            }, {
                "title": "$ u''(x) − 2u(x) = 4x,u(0) = 0, u′(0) = 2 $ "
            }, {
                "title": "$ u′(x) + u(x) = 0, u(0) = 1 $ "
            }, {
                "title": "$ u''(x) − 4u(x) = 24x,u(0) = 0, u′(0) = 0 $ "
            }],
            "answer": 1
        }, {
            "question": "<span class=\"highlighted\">$ F(x) = \\int_{x}^{x^2} ln(1  + xt) dt \\Rightarrow F'(x) = ? $</span>",
            "variants": [{
                "title": "$ 2xln(1 + x^3) - ln(1 + x^2) $ "
            }, {
                "title": "$ 2xln(1 + x^3) - ln(1 + x^2) +  \\int_{x}^{x^2} \\frac{t}{1 + xt} dt $ "
            }, {
                "title": "$ 2xln(1 + x^3) + ln(1 + x^2) + \\int_{x}^{x^2} \\frac{t}{1 - xt} dt $ "
            }, {
                "title": "$   \\int_{x}^{x^2} \\frac{t}{1 + xt} dt $ "
            }, {
                "title": "$ ln(1 + x^3) - ln(1 + x^2) + \\int_{x}^{x^2} \\frac{t}{1 - xt} dt $ "
            }],
            "answer": 1
        }, {
            "question": "<span class=\"highlighted\">What </span>is the value of <span class=\"highlighted\">$ f(x) =? $</span><br>If    <span class=\"highlighted\">$ u(x) = e^x $  </span><br><span class=\"highlighted\">is a solution of the V</span><span class=\"highlighted\">olterra  </span><span class=\"highlighted\">integral equation</span><br><span class=\"highlighted\">$ u(x) = f(x) + \\int_{0}^{x}(x - t)u(t) \\ dt $</span>",
            "variants": [{
                "title": "$ 1 + x $ "
            }, {
                "title": "$ e^x $ "
            }, {
                "title": "$ \\sin x $ "
            }, {
                "title": "$ x $ "
            }, {
                "title": "$ 2x $ "
            }],
            "answer": 0
        }, {
            "question": "<span class=\"highlighted\">Which </span>is the equivalent <span class=\"highlighted\">IVP </span>to the <span class=\"highlighted\">Integral equation</span><br><span class=\"highlighted\">$ u(x) = x^2 + \\frac{1}{6}\\int_{0}^{x} (x - t)^3 u(t) dt \\ ? $</span>",
            "variants": [{
                "title": "$ u^{(4)}(x) - u(x) = 0, u(0) = u′(0) = u'''(0) = 0,\\ u''(0) = 2  $ "
            }, {
                "title": "$ u''(x) - u(x) = \\cos x, u(0) = 0,\\ u′(0) = 0 $ "
            }, {
                "title": "$ u^{(4)}(x) + u(x) = 1, u(0) = u′(0) = u'''(0) = 0,\\ u''(0) = 2 $ "
            }, {
                "title": "$ u^{(4)}(x) - 4u(x) = 0, u(0) = u′(0) = u'''(0) = 2,\\ u''(0) = 0 $ "
            }, {
                "title": "$ u'''(x) = 2u'(x) + u(x), u(0) = u′(0) = 1, u''(0) =0 $ "
            }],
            "answer": 0
        }, {
            "question": "<span class=\"highlighted\">$ F(x) = \\int_{0}^{x} (x - t)^3 u(t) dt \\Rightarrow F''(x) = ? $</span>",
            "variants": [{
                "title": "$ \\int_{0}^{x}3(x - t)^2 u(t) dt $ "
            }, {
                "title": "$ u(x) $ "
            }, {
                "title": "$ 6 u(x) $ "
            }, {
                "title": "$ \\int_{0}^{x}6(x - t) u(t) dt $ "
            }, {
                "title": "$ \\int_{0}^{x}6 u(t) dt $ "
            }],
            "answer": 3
        },
        {
            "question": "<span class=\"highlighted\">Which </span>is the equivalent <span class=\"highlighted\">IVP </span>to the <span class=\"highlighted\">Integral equation</span><br><span class=\"highlighted\">$ u(x) = x - \\cos x + \\int_{0}^{x} (x - t) u(t) dt \\ ? $</span>",
            "variants": [{
                "title": "$ u''(x) - u'(x) = 0; \\ u(0) =1,u'(0) = 1 $ "
            }, {
                "title": "$ u''(x) - u(x) = \\cos x, u(0) = - 1, \\ u′(0) = 1 $ "
            }, {
                "title": "$ u''(x) - u'(x) = \\cos x, u(0) = 0, \\ u′(0) = 0 $ "
            }, {
                "title": "$ u''(x) - u(x) = \\sin x, u(0) = - 1, \\ u′(0) = 1 $ "
            }, {
                "title": "$ u''(x) + u(x) = \\cos x, u(0) = - 1, \\ u′(0) = 1 $ "
            }],
            "answer": 1
        }, {
            "question": "<span class=\"highlighted\">Which </span>is the equivalent <span class=\"highlighted\">IVP </span>to the <span class=\"highlighted\">Integral equation</span><br><span class=\"highlighted\">$ u(x) = 1 + \\int_{0}^{x} u(t) dt \\ ? $</span>",
            "variants": [{
                "title": "$ u'(x) - u(x) = 0; \\ u(0) = 0 $ "
            }, {
                "title": "$ u'(x) + u(x) = 0; \\ u(0) =1 $ "
            }, {
                "title": "$ u''(x) - u(x) = 0; \\ u(0) =1 $ "
            }, {
                "title": "$ u''(x) - u'(x) = 0; \\ u(0) =1,u'(0) = 1 $ "
            }, {
                "title": "$ u'(x) - u(x) = 0; \\ u(0) =1 $ "
            }],
            "answer": 4
        }, {
            "question": "<span class=\"highlighted\">$ \\frac{d}{dx}\\int_{0}^{x}(x - t)^3 u(t)dt = ? $</span>",
            "variants": [{
                "title": "$ \\int_{0}^{x}(x - t)^2u(t)dt $ "
            }, {
                "title": "$ \\int_{0}^{x}(x + t)^4u(t)dt $ "
            }, {
                "title": "$ \\int_{0}^{x}3(x - t)u(t)dt $ "
            }, {
                "title": "$ \\int_{0}^{x}3(x - t)^2u(t)dt $ "
            }, {
                "title": "$ \\int_{0}^{x}3(x + t)^2u(t)dt $ "
            }],
            "answer": 3
        }, {
            "question": "<span class=\"highlighted\">$ F(x) = \\int_{0}^{x} \\cosh(x^3+ t^3) dt \\Rightarrow F'(x) = ? $</span>",
            "variants": [{
                "title": "$ \\cosh(2x^3) + \\int_{0}^{x} 3x^2\\sinh (x^3 + t^3) dt $ "
            }, {
                "title": "$ \\sinh(2x^3) + \\int_{0}^{x} 3x^2\\sinh (x^3 + t^3) dt $ "
            }, {
                "title": "$ \\cosh(2x^3) + \\int_{0}^{x} 3x^2\\cosh (x^3 + t^3) dt $ "
            }, {
                "title": "$ \\cos(2x^3) + \\int_{0}^{x} 3x^2\\sin (x^3 + t^3) dt $ "
            }, {
                "title": "$ \\cosh(2x) + \\int_{0}^{x} 3x\\sinh (x + t) dt $ "
            }],
            "answer": 0
        },
        {
            "question": "<span class=\"highlighted\">$ \\frac{d^2}{dx^2}(\\int_{0}^{x} (x - t) u(t)dt) = ? $</span>",
            "variants": [{
                "title": "$ x^2 $ "
            }, {
                "title": "$ u(x) $ "
            }, {
                "title": "$ u''(x) $ "
            }, {
                "title": "$ u'(x) $ "
            }, {
                "title": "$ x $ "
            }],
            "answer": 1
        }, {
            "question": "<span class=\"highlighted\">Which </span>is the equivalent <span class=\"highlighted\">IVP </span>to the <span class=\"highlighted\">Integral equation</span><br><span class=\"highlighted\">$ u(x) = x + \\int_{0}^{x}(t - x) u(t) dt \\ ? $</span>",
            "variants": [{
                "title": "$ u''(x) + u(x) = 0; \\ u(0) =1, \\ u'(0) = 1 $ "
            }, {
                "title": "$ u'(x) + u(x) = 0; \\ u(0) =1 $ "
            }, {
                "title": "$ u'(x) - u(x) = 0; \\ u(0) = 0 $ "
            }, {
                "title": "$ u''(x) - u'(x) = 0; \\ u(0) =1,u'(0) = 1 $ "
            }, {
                "title": "$ u''(x) - u(x) = 0; \\ u(0) =1 $ "
            }],
            "answer": 0
        }, {
            "question": "<span class=\"highlighted\">$ F(x) = \\int_{0}^{x} (x - t)^3 u(t) dt \\Rightarrow F^{(iv)}(x) = ? $</span>",
            "variants": [{
                "title": "$ \\int_{0}^{x}6(x - t) u(t) dt $ "
            }, {
                "title": "$ \\int_{0}^{x}3(x - t)^2 u(t) dt $ "
            }, {
                "title": "$ u(x) $ "
            }, {
                "title": "$ 6 u(x) $ "
            }, {
                "title": "$ \\int_{0}^{x}6 u(t) dt $ "
            }],
            "answer": 3
        }, {
            "question": "<span class=\"highlighted\">Which </span>is the equivalent <span class=\"highlighted\">IVP </span>to the <span class=\"highlighted\">Integral equation</span><br><span class=\"highlighted\">$ u(x) = 2 + 3x + 5x^2 + \\int_{0}^{x}[ 1 + 2 (x - t)] u(t) dt \\ ? $</span>",
            "variants": [{
                "title": "$ u''(x) - u'(x) - 2u(x) = 10, u(0) = 2, \\ u′(0) = 5 $ "
            }, {
                "title": "$ u''(x) - 3u'(x) - u(x) = 10, u(0) = 0, \\ u′(0) = 0 $ "
            }, {
                "title": "$ u''(x) - u'(x) - 2u(x) = 1, u(0) = 5, \\ u′(0) = 2$ "
            }, {
                "title": "$ u''(x) - u'(x) - 2u(x) = 0, u(0) = 2, \\ u′(0) = 5 $ "
            }, {
                "title": "$ u''(x) + u'(x) + 2u(x) = 10, u(0) = 2, \\ u′(0) = 5 $ "
            }],
            "answer": 0
        },
        {
            "question": "<br>The <span class=\"highlighted\">standard form</span> of a<span class=\"highlighted\">  Fredholm linear integral equation</span>  <span class=\"highlighted\">of 2.kind</span> is of the form <br/><br><span class=\"highlighted\">$ f(x) =  \\lambda \\int_{a}^{b}\\ K(x,t) \\ u(t)\\ dt, \\ \\ a \\leq x,t \\leq b $</span>",
            "variants": [{
                "title": "True "
            }, {
                "title": "False "
            }],
            "answer": 1
        }, {
            "question": "<br>The <span class=\"highlighted\">standard form</span> of a<span class=\"highlighted\">  Fredholm linear integral equation</span>  is of the form <br/><br><span class=\"highlighted\">$  \\psi(x) u(x) = f(x) + \\lambda \\int_{a}^{b}\\ K(x,t) \\ u(t)\\ dt, \\ \\ a \\leq x,t \\leq b  $</span>",
            "variants": [{
                "title": "True "
            }, {
                "title": "False "
            }],
            "answer": 0
        },
        {
            "question": "<br>The <span class=\"highlighted\">standard form</span> of a<span class=\"highlighted\">  Fredholm linear integral equation</span>  <span class=\"highlighted\">of 2.kind</span> is of the form <br/><br><span class=\"highlighted\">$ u(x) = f(x) + \\lambda \\int_{a}^{b}\\ K(x,t) \\ u(t)\\ dt, \\ \\ a \\leq x,t \\leq b $</span>",
            "variants": [{
                "title": "True "
            }, {
                "title": "False "
            }],
            "answer": 0
        },
        {
            "question": "<span class=\"highlighted\">Which </span>is the equivalent <span class=\"highlighted\">IVP </span>to the <span class=\"highlighted\">Integral equation</span><br><span class=\"highlighted\">$ u(x) = x - \\cos x + \\int_{0}^{x} (x - t) u(t) dt \\ ? $</span>",
            "variants": [{
                "title": "$ u''(x) - u'(x) = 0; \\ u(0) =1,u'(0) = 1 $ "
            }, {
                "title": "$ u''(x) - u(x) = \\cos x, u(0) = - 1, \\ u′(0) = 1 $ "
            }, {
                "title": "$ u''(x) - u'(x) = \\cos x, u(0) = 0, \\ u′(0) = 0 $ "
            }, {
                "title": "$ u''(x) - u(x) = \\sin x, u(0) = - 1, \\ u′(0) = 1 $ "
            }, {
                "title": "$ u''(x) + u(x) = \\cos x, u(0) = - 1, \\ u′(0) = 1 $ "
            }],
            "answer": 1
        }, {
            "question": "<span class=\"highlighted\">Which </span>is the equivalent <span class=\"highlighted\">IVP </span>to the <span class=\"highlighted\">Integral equation</span><br><span class=\"highlighted\">$ u(x) = 1 + \\int_{0}^{x} u(t) dt \\ ? $</span>",
            "variants": [{
                "title": "$ u'(x) - u(x) = 0; \\ u(0) = 0 $ "
            }, {
                "title": "$ u'(x) + u(x) = 0; \\ u(0) =1 $ "
            }, {
                "title": "$ u''(x) - u(x) = 0; \\ u(0) =1 $ "
            }, {
                "title": "$ u''(x) - u'(x) = 0; \\ u(0) =1,u'(0) = 1 $ "
            }, {
                "title": "$ u'(x) - u(x) = 0; \\ u(0) =1 $ "
            }],
            "answer": 4
        }, {
            "question": "<span class=\"highlighted\">$ \\frac{d}{dx}\\int_{0}^{x}(x - t)^3 u(t)dt = ? $</span>",
            "variants": [{
                "title": "$ \\int_{0}^{x}(x - t)^2u(t)dt $ "
            }, {
                "title": "$ \\int_{0}^{x}(x + t)^4u(t)dt $ "
            }, {
                "title": "$ \\int_{0}^{x}3(x - t)u(t)dt $ "
            }, {
                "title": "$ \\int_{0}^{x}3(x - t)^2u(t)dt $ "
            }, {
                "title": "$ \\int_{0}^{x}3(x + t)^2u(t)dt $ "
            }],
            "answer": 3
        }, {
            "question": "<span class=\"highlighted\">$ F(x) = \\int_{0}^{x} \\cosh(x^3+ t^3) dt \\Rightarrow F'(x) = ? $</span>",
            "variants": [{
                "title": "$ \\cosh(2x^3) + \\int_{0}^{x} 3x^2\\sinh (x^3 + t^3) dt $ "
            }, {
                "title": "$ \\sinh(2x^3) + \\int_{0}^{x} 3x^2\\sinh (x^3 + t^3) dt $ "
            }, {
                "title": "$ \\cosh(2x^3) + \\int_{0}^{x} 3x^2\\cosh (x^3 + t^3) dt $ "
            }, {
                "title": "$ \\cos(2x^3) + \\int_{0}^{x} 3x^2\\sin (x^3 + t^3) dt $ "
            }, {
                "title": "$ \\cosh(2x) + \\int_{0}^{x} 3x\\sinh (x + t) dt $ "
            }],
            "answer": 0
        },
        {
            "question": "<br>The <span class=\"highlighted\">standard form</span> of a<span class=\"highlighted\">  Fredholm linear integral equation</span>  <span class=\"highlighted\">of 1.kind</span> is of the form <br/><br><span class=\"highlighted\">$ u(x) =  \\lambda \\int_{a}^{b}\\ K(x,t) \\ u(t)\\ dt, \\ \\ a \\leq x,t \\leq b $</span>",
            "variants": [{
                "title": "True "
            }, {
                "title": "False "
            }],
            "answer": 1
        }, {
            "question": "<span class=\"highlighted\">Which</span> of the following is correct  <br><span class=\"highlighted\">classification </span>of the <span class=\"highlighted\">integral equation?</span><br><span class=\"highlighted\">$ u(x) = 1 + \\int_{0}^{x} sin(u(t))dt $</span>",
            "variants": [{
                "title": "Volterra, nonlinear, nonhomogeneous "
            }, {
                "title": "Fredholm, linear, homogeneous "
            }, {
                "title": "Volterra, linear, nonhomogeneous "
            }, {
                "title": "Fredholm, nonlinear, homogeneous "
            }, {
                "title": "Volterra, nonlinear, homogeneous "
            }],
            "answer": 0
        }, {
            "question": "<span class=\"highlighted\">Which</span> of the following is correct  <br><span class=\"highlighted\">classification </span>of the <span class=\"highlighted\">integral equation?</span><br><span class=\"highlighted\">$ u(x) = 1 + x^2 +  \\int_{0}^{x} (x - t)u(t)dt $</span>",
            "variants": [{
                "title": "Volterra, linear, homogeneous "
            }, {
                "title": "Volterra, linear, nonhomogeneous "
            }, {
                "title": "Fredholm, linear, homogeneous "
            }, {
                "title": "Volterra, nonlinear, homogeneous "
            }, {
                "title": "Fredholm, nonlinear, homogeneous "
            }],
            "answer": 1
        },
        {
            "question": "<span class=\"highlighted\">Which</span> of the following is correct  <br><span class=\"highlighted\">classification </span>of the <span class=\"highlighted\">integral equation?</span><br><span class=\"highlighted\">$ u(x) = 1 + \\frac{x}{4} + \\int_{0}^{x} \\frac{1}{x + 4}\\frac{1}{u(t)} dt $</span>",
            "variants": [{
                "title": "Nonhomogeneous nonlinear Volterra integral equation "
            }, {
                "title": "Nonlinear Volterra integro-differential equation "
            }, {
                "title": "Linear Fredholm integro-differential equation "
            }, {
                "title": "Nonhomogeneous linear Fredholm integral equation "
            }, {
                "title": "Nonhomogeneous linear Volterra integral equation "
            }],
            "answer": 0
        }
    ]
}